{
  "2026-02-25": {
    "checks": {
      "0-0": true,
      "0-1": true,
      "0-2": true,
      "3-0": true,
      "3-1": true,
      "3-4": true,
      "3-5": true,
      "3-6": true,
      "3-9": false,
      "4-0": true,
      "4-4": true,
      "4-3": true,
      "5-0": true,
      "6-0": true,
      "9-0": true
    },
    "note": "",
    "mood": 0,
    "energy": 0,
    "graceUsed": []
  },
  "2026-02-23": {
    "checks": {
      "0-0": true,
      "0-1": true,
      "0-2": true
    },
    "note": "",
    "mood": 4,
    "energy": 3,
    "graceUsed": []
  }
}